README.rst
setup.cfg
setup.py
oaas_grpc/__init__.py
oaas_grpc/py.typed
oaas_grpc.egg-info/PKG-INFO
oaas_grpc.egg-info/SOURCES.txt
oaas_grpc.egg-info/dependency_links.txt
oaas_grpc.egg-info/requires.txt
oaas_grpc.egg-info/top_level.txt
oaas_grpc/client/__init__.py
oaas_grpc/client/client.py
oaas_grpc/client/connection_test.py
oaas_grpc/client/grpc_proxy_instance_handler.py
oaas_grpc/client/oaas_registry.py
oaas_grpc/client/proxy.py
oaas_grpc/client/registry_discovery.py
oaas_grpc/rpc/__init__.py
oaas_grpc/server/__init__.py
oaas_grpc/server/find_ips.py
oaas_grpc/server/server.py
test/__init__.py
test/test_delegate_method.py
test/test_retry_strategy.py