Metadata-Version: 1.0
Name: oaas-grpc
Version: 1.1.1
Summary: oaas_grpc
Home-page: UNKNOWN
Author: Bogdan Mustiata
Author-email: bogdan.mustiata@gmail.com
License: BSD
Platform: UNKNOWN
